{
  "generatedAt": "2026-05-08T18:00:27.107Z",
  "technology": {
    "slug": "azure-devops-ado-checklist",
    "technology": "Azure DevOps",
    "status": "Preview",
    "maturityBucket": "Preview",
    "itemCount": 57,
    "highSeverityCount": 14,
    "categories": [
      "Azure Artifact",
      "Azure Boards",
      "Azure Pipelines",
      "DevOps Practice",
      "Version Control"
    ],
    "services": [],
    "wafPillars": [
      "Operations",
      "Security"
    ],
    "sourcePath": "checklists/ado_checklist.en.json",
    "sourceUrl": "https://github.com/Azure/review-checklists/blob/main/checklists/ado_checklist.en.json",
    "timestamp": "12/15/2023 11:48:52",
    "sourceKind": "checklists",
    "description": "Azure DevOps is a Preview family with 57 normalized items, 14 high-severity findings, covers Azure Artifact, Azure Boards, Azure Pipelines, and uses generalized guidance.",
    "whatThisMeans": "Use to enrich design reviews, but validate recommendations before treating them as baseline controls.",
    "quality": {
      "label": "Preview · Medium confidence",
      "qualityScore": 89,
      "metadataCompleteness": 83,
      "severityConfidence": 100,
      "sourceCoverageQuality": 100,
      "recommendedUsageConfidence": "Medium",
      "generatedDate": "2026-05-08T18:00:27.107Z",
      "maturityBucket": "Preview",
      "summary": "Use with architectural judgment. Preview content is valuable, but it should not be treated as equivalent to mature review baselines."
    }
  },
  "items": [
    {
      "guid": "eda1dae2-cc85-4c47-a6b7-81cca0e6c465",
      "technology": "Azure DevOps",
      "technologySlug": "azure-devops-ado-checklist",
      "technologyStatus": "Preview",
      "technologyMaturityBucket": "Preview",
      "usageConfidence": "Medium",
      "technologyQualityScore": 89,
      "family": "Azure DevOps",
      "sourceKind": "checklists",
      "checklist": "Azure DevOps",
      "category": "Version Control",
      "subcategory": "Branching Policy",
      "id": "A01.01",
      "text": "Branch Policies",
      "description": "Implement branching policy in Azure DevOps",
      "severity": "High",
      "waf": "Operations",
      "link": "https://learn.microsoft.com/azure/devops/repos/git/branch-policies-overview?view=azure-devops",
      "sourcePath": "checklists/ado_checklist.en.json",
      "sourceUrl": "https://github.com/Azure/review-checklists/blob/main/checklists/ado_checklist.en.json",
      "normalizedAt": "2026-05-08T18:00:27.107Z",
      "provenance": {
        "technology": "normalized",
        "technologyStatus": "normalized",
        "category": "source",
        "subcategory": "source",
        "severity": "normalized",
        "waf": "normalized",
        "service": "unavailable",
        "description": "source"
      }
    },
    {
      "guid": "bc288bec-6a16-4ca7-8444-51e1add34529",
      "technology": "Azure DevOps",
      "technologySlug": "azure-devops-ado-checklist",
      "technologyStatus": "Preview",
      "technologyMaturityBucket": "Preview",
      "usageConfidence": "Medium",
      "technologyQualityScore": 89,
      "family": "Azure DevOps",
      "sourceKind": "checklists",
      "checklist": "Azure DevOps",
      "category": "Version Control",
      "subcategory": "Branching Policy",
      "id": "A01.02",
      "text": "Branching strategy",
      "description": "Understand branch strategy such as GitFlow or GitHub Flow",
      "severity": "High",
      "waf": "Operations",
      "link": "https://learn.microsoft.com/azure/devops/repos/git/git-branching-guidance?view=azure-devops",
      "sourcePath": "checklists/ado_checklist.en.json",
      "sourceUrl": "https://github.com/Azure/review-checklists/blob/main/checklists/ado_checklist.en.json",
      "normalizedAt": "2026-05-08T18:00:27.107Z",
      "provenance": {
        "technology": "normalized",
        "technologyStatus": "normalized",
        "category": "source",
        "subcategory": "source",
        "severity": "normalized",
        "waf": "normalized",
        "service": "unavailable",
        "description": "source"
      }
    },
    {
      "guid": "ec723823-7a15-41c5-ab4e-401914387e5c",
      "technology": "Azure DevOps",
      "technologySlug": "azure-devops-ado-checklist",
      "technologyStatus": "Preview",
      "technologyMaturityBucket": "Preview",
      "usageConfidence": "Medium",
      "technologyQualityScore": 89,
      "family": "Azure DevOps",
      "sourceKind": "checklists",
      "checklist": "Azure DevOps",
      "category": "Version Control",
      "subcategory": "Branching Policy",
      "id": "A01.03",
      "text": "Understand GitFlow Branch Strategy",
      "description": "Understand how teams work with git",
      "severity": "High",
      "waf": "Operations",
      "link": "https://www.atlassian.com/git/tutorials/comparing-workflows/gitflow-workflow",
      "sourcePath": "checklists/ado_checklist.en.json",
      "sourceUrl": "https://github.com/Azure/review-checklists/blob/main/checklists/ado_checklist.en.json",
      "normalizedAt": "2026-05-08T18:00:27.107Z",
      "provenance": {
        "technology": "normalized",
        "technologyStatus": "normalized",
        "category": "source",
        "subcategory": "source",
        "severity": "normalized",
        "waf": "normalized",
        "service": "unavailable",
        "description": "source"
      }
    },
    {
      "guid": "a9c26c9c-32ab-45bd-8c69-98a246e33899",
      "technology": "Azure DevOps",
      "technologySlug": "azure-devops-ado-checklist",
      "technologyStatus": "Preview",
      "technologyMaturityBucket": "Preview",
      "usageConfidence": "Medium",
      "technologyQualityScore": 89,
      "family": "Azure DevOps",
      "sourceKind": "checklists",
      "checklist": "Azure DevOps",
      "category": "Version Control",
      "subcategory": "Branching Policy",
      "id": "A01.04",
      "text": "Pull Request Review",
      "description": "Merge into higher branches after two or more reviewers in a PR",
      "severity": "High",
      "waf": "Operations",
      "link": "https://learn.microsoft.com/azure/devops/repos/git/review-pull-requests?view=azure-devops&tabs=browser",
      "sourcePath": "checklists/ado_checklist.en.json",
      "sourceUrl": "https://github.com/Azure/review-checklists/blob/main/checklists/ado_checklist.en.json",
      "normalizedAt": "2026-05-08T18:00:27.107Z",
      "provenance": {
        "technology": "normalized",
        "technologyStatus": "normalized",
        "category": "source",
        "subcategory": "source",
        "severity": "normalized",
        "waf": "normalized",
        "service": "unavailable",
        "description": "source"
      }
    },
    {
      "guid": "7e41c77d-68cb-46a2-8ac1-9f916d697d8e",
      "technology": "Azure DevOps",
      "technologySlug": "azure-devops-ado-checklist",
      "technologyStatus": "Preview",
      "technologyMaturityBucket": "Preview",
      "usageConfidence": "Medium",
      "technologyQualityScore": 89,
      "family": "Azure DevOps",
      "sourceKind": "checklists",
      "checklist": "Azure DevOps",
      "category": "Version Control",
      "subcategory": "Branching Policy",
      "id": "A01.05",
      "text": "Access Control to the Branch",
      "description": "Implement access control to the branches",
      "severity": "Medium",
      "waf": "Operations",
      "link": "https://learn.microsoft.com/azure/devops/repos/git/branch-permissions?view=azure-devops",
      "sourcePath": "checklists/ado_checklist.en.json",
      "sourceUrl": "https://github.com/Azure/review-checklists/blob/main/checklists/ado_checklist.en.json",
      "normalizedAt": "2026-05-08T18:00:27.107Z",
      "provenance": {
        "technology": "normalized",
        "technologyStatus": "normalized",
        "category": "source",
        "subcategory": "source",
        "severity": "normalized",
        "waf": "normalized",
        "service": "unavailable",
        "description": "source"
      }
    },
    {
      "guid": "adfd27bd-e187-401a-a252-baa9b68a088c",
      "technology": "Azure DevOps",
      "technologySlug": "azure-devops-ado-checklist",
      "technologyStatus": "Preview",
      "technologyMaturityBucket": "Preview",
      "usageConfidence": "Medium",
      "technologyQualityScore": 89,
      "family": "Azure DevOps",
      "sourceKind": "checklists",
      "checklist": "Azure DevOps",
      "category": "Version Control",
      "subcategory": "Security",
      "id": "A02.01",
      "text": "Code Scan",
      "description": "Perform SAST code scan",
      "severity": "High",
      "waf": "Security",
      "link": "https://devblogs.microsoft.com/devops/integrate-security-into-your-developer-workflow-with-github-advanced-security-for-azure-devops/",
      "sourcePath": "checklists/ado_checklist.en.json",
      "sourceUrl": "https://github.com/Azure/review-checklists/blob/main/checklists/ado_checklist.en.json",
      "normalizedAt": "2026-05-08T18:00:27.107Z",
      "provenance": {
        "technology": "normalized",
        "technologyStatus": "normalized",
        "category": "source",
        "subcategory": "source",
        "severity": "normalized",
        "waf": "normalized",
        "service": "unavailable",
        "description": "source"
      }
    },
    {
      "guid": "9a8f822b-8eb9-4d1b-a77f-26e5e6beba8e",
      "technology": "Azure DevOps",
      "technologySlug": "azure-devops-ado-checklist",
      "technologyStatus": "Preview",
      "technologyMaturityBucket": "Preview",
      "usageConfidence": "Medium",
      "technologyQualityScore": 89,
      "family": "Azure DevOps",
      "sourceKind": "checklists",
      "checklist": "Azure DevOps",
      "category": "Version Control",
      "subcategory": "Practice",
      "id": "A03.01",
      "text": "TFVC as Code Repository",
      "description": "Understand TFVC as Code Repo",
      "severity": "Low",
      "waf": "Operations",
      "link": "https://learn.microsoft.com/azure/devops/repos/tfvc/what-is-tfvc?view=azure-devops",
      "sourcePath": "checklists/ado_checklist.en.json",
      "sourceUrl": "https://github.com/Azure/review-checklists/blob/main/checklists/ado_checklist.en.json",
      "normalizedAt": "2026-05-08T18:00:27.107Z",
      "provenance": {
        "technology": "normalized",
        "technologyStatus": "normalized",
        "category": "source",
        "subcategory": "source",
        "severity": "normalized",
        "waf": "normalized",
        "service": "unavailable",
        "description": "source"
      }
    },
    {
      "guid": "d4f3437b-c336-4d71-9f27-a71eee0b9b5d",
      "technology": "Azure DevOps",
      "technologySlug": "azure-devops-ado-checklist",
      "technologyStatus": "Preview",
      "technologyMaturityBucket": "Preview",
      "usageConfidence": "Medium",
      "technologyQualityScore": 89,
      "family": "Azure DevOps",
      "sourceKind": "checklists",
      "checklist": "Azure DevOps",
      "category": "Version Control",
      "subcategory": "Practice",
      "id": "A03.02",
      "text": "Choose Right version control",
      "description": "Compare Git vs TFVC for your project",
      "severity": "Low",
      "waf": "Operations",
      "link": "https://learn.microsoft.com/azure/devops/repos/tfvc/comparison-git-tfvc?view=azure-devops",
      "sourcePath": "checklists/ado_checklist.en.json",
      "sourceUrl": "https://github.com/Azure/review-checklists/blob/main/checklists/ado_checklist.en.json",
      "normalizedAt": "2026-05-08T18:00:27.107Z",
      "provenance": {
        "technology": "normalized",
        "technologyStatus": "normalized",
        "category": "source",
        "subcategory": "source",
        "severity": "normalized",
        "waf": "normalized",
        "service": "unavailable",
        "description": "source"
      }
    },
    {
      "guid": "8defd5d7-21d4-41d2-900c-807bf9eab40f",
      "technology": "Azure DevOps",
      "technologySlug": "azure-devops-ado-checklist",
      "technologyStatus": "Preview",
      "technologyMaturityBucket": "Preview",
      "usageConfidence": "Medium",
      "technologyQualityScore": 89,
      "family": "Azure DevOps",
      "sourceKind": "checklists",
      "checklist": "Azure DevOps",
      "category": "Azure Boards",
      "subcategory": "Team Planning",
      "id": "B01.01",
      "text": "Configure your teams",
      "description": "Set up your team management",
      "severity": "High",
      "waf": "Operations",
      "link": "https://learn.microsoft.com/azure/devops/organizations/settings/manage-teams?view=azure-devops",
      "sourcePath": "checklists/ado_checklist.en.json",
      "sourceUrl": "https://github.com/Azure/review-checklists/blob/main/checklists/ado_checklist.en.json",
      "normalizedAt": "2026-05-08T18:00:27.107Z",
      "provenance": {
        "technology": "normalized",
        "technologyStatus": "normalized",
        "category": "source",
        "subcategory": "source",
        "severity": "normalized",
        "waf": "normalized",
        "service": "unavailable",
        "description": "source"
      }
    },
    {
      "guid": "9ed5b354-78d4-447a-a26c-2863c00f1cac",
      "technology": "Azure DevOps",
      "technologySlug": "azure-devops-ado-checklist",
      "technologyStatus": "Preview",
      "technologyMaturityBucket": "Preview",
      "usageConfidence": "Medium",
      "technologyQualityScore": 89,
      "family": "Azure DevOps",
      "sourceKind": "checklists",
      "checklist": "Azure DevOps",
      "category": "Azure Boards",
      "subcategory": "Team Planning",
      "id": "B01.02",
      "text": "Configure your sprints",
      "description": "Start scheduling sprints",
      "severity": "Medium",
      "waf": "Operations",
      "link": "https://learn.microsoft.com/azure/devops/boards/sprints/define-sprints?view=azure-devops",
      "sourcePath": "checklists/ado_checklist.en.json",
      "sourceUrl": "https://github.com/Azure/review-checklists/blob/main/checklists/ado_checklist.en.json",
      "normalizedAt": "2026-05-08T18:00:27.107Z",
      "provenance": {
        "technology": "normalized",
        "technologyStatus": "normalized",
        "category": "source",
        "subcategory": "source",
        "severity": "normalized",
        "waf": "normalized",
        "service": "unavailable",
        "description": "source"
      }
    },
    {
      "guid": "699ef1d5-a83d-4e5d-b36c-1c81870a0bc5",
      "technology": "Azure DevOps",
      "technologySlug": "azure-devops-ado-checklist",
      "technologyStatus": "Preview",
      "technologyMaturityBucket": "Preview",
      "usageConfidence": "Medium",
      "technologyQualityScore": 89,
      "family": "Azure DevOps",
      "sourceKind": "checklists",
      "checklist": "Azure DevOps",
      "category": "Azure Boards",
      "subcategory": "Team Planning",
      "id": "B01.03",
      "text": "Choose Work Item types",
      "description": "Set up your work item heirarchy",
      "severity": "Low",
      "waf": "Operations",
      "link": "https://learn.microsoft.com/azure/devops/organizations/settings/work/customize-process-work-item-type?view=azure-devops",
      "sourcePath": "checklists/ado_checklist.en.json",
      "sourceUrl": "https://github.com/Azure/review-checklists/blob/main/checklists/ado_checklist.en.json",
      "normalizedAt": "2026-05-08T18:00:27.107Z",
      "provenance": {
        "technology": "normalized",
        "technologyStatus": "normalized",
        "category": "source",
        "subcategory": "source",
        "severity": "normalized",
        "waf": "normalized",
        "service": "unavailable",
        "description": "source"
      }
    },
    {
      "guid": "c1e43a18-658d-4285-aed6-7179b825546d",
      "technology": "Azure DevOps",
      "technologySlug": "azure-devops-ado-checklist",
      "technologyStatus": "Preview",
      "technologyMaturityBucket": "Preview",
      "usageConfidence": "Medium",
      "technologyQualityScore": 89,
      "family": "Azure DevOps",
      "sourceKind": "checklists",
      "checklist": "Azure DevOps",
      "category": "Azure Boards",
      "subcategory": "Team Planning",
      "id": "B01.04",
      "text": "Select a WIT Process",
      "description": "WIT Processes available in Azure DevOps",
      "severity": "High",
      "waf": "Operations",
      "link": "https://learn.microsoft.com/azure/devops/boards/work-items/guidance/choose-process?view=azure-devops&tabs=agile-process",
      "sourcePath": "checklists/ado_checklist.en.json",
      "sourceUrl": "https://github.com/Azure/review-checklists/blob/main/checklists/ado_checklist.en.json",
      "normalizedAt": "2026-05-08T18:00:27.107Z",
      "provenance": {
        "technology": "normalized",
        "technologyStatus": "normalized",
        "category": "source",
        "subcategory": "source",
        "severity": "normalized",
        "waf": "normalized",
        "service": "unavailable",
        "description": "source"
      }
    },
    {
      "guid": "f2aee455-3afc-4833-a248-726dd68c5b5c",
      "technology": "Azure DevOps",
      "technologySlug": "azure-devops-ado-checklist",
      "technologyStatus": "Preview",
      "technologyMaturityBucket": "Preview",
      "usageConfidence": "Medium",
      "technologyQualityScore": 89,
      "family": "Azure DevOps",
      "sourceKind": "checklists",
      "checklist": "Azure DevOps",
      "category": "Azure Boards",
      "subcategory": "Tool Integration",
      "id": "B02.01",
      "text": "GitHub Integration",
      "description": "Use Azure Boards with GitHub",
      "severity": "Low",
      "waf": "Operations",
      "link": "https://learn.microsoft.com/azure/devops/cross-service/github-integration?view=azure-devops",
      "sourcePath": "checklists/ado_checklist.en.json",
      "sourceUrl": "https://github.com/Azure/review-checklists/blob/main/checklists/ado_checklist.en.json",
      "normalizedAt": "2026-05-08T18:00:27.107Z",
      "provenance": {
        "technology": "normalized",
        "technologyStatus": "normalized",
        "category": "source",
        "subcategory": "source",
        "severity": "normalized",
        "waf": "normalized",
        "service": "unavailable",
        "description": "source"
      }
    },
    {
      "guid": "2925394b-69b9-4d37-aac4-3bc68d1d7665",
      "technology": "Azure DevOps",
      "technologySlug": "azure-devops-ado-checklist",
      "technologyStatus": "Preview",
      "technologyMaturityBucket": "Preview",
      "usageConfidence": "Medium",
      "technologyQualityScore": 89,
      "family": "Azure DevOps",
      "sourceKind": "checklists",
      "checklist": "Azure DevOps",
      "category": "Azure Boards",
      "subcategory": "Process Planning",
      "id": "B03.01",
      "text": "Understand Agile Vs Scrum",
      "description": "Understand the methologies",
      "severity": "Medium",
      "waf": "Operations",
      "link": "https://www.atlassian.com/agile/scrum/agile-vs-scrum",
      "sourcePath": "checklists/ado_checklist.en.json",
      "sourceUrl": "https://github.com/Azure/review-checklists/blob/main/checklists/ado_checklist.en.json",
      "normalizedAt": "2026-05-08T18:00:27.107Z",
      "provenance": {
        "technology": "normalized",
        "technologyStatus": "normalized",
        "category": "source",
        "subcategory": "source",
        "severity": "normalized",
        "waf": "normalized",
        "service": "unavailable",
        "description": "source"
      }
    },
    {
      "guid": "7246b448-564b-44dd-94a7-59c7633bd2a1",
      "technology": "Azure DevOps",
      "technologySlug": "azure-devops-ado-checklist",
      "technologyStatus": "Preview",
      "technologyMaturityBucket": "Preview",
      "usageConfidence": "Medium",
      "technologyQualityScore": 89,
      "family": "Azure DevOps",
      "sourceKind": "checklists",
      "checklist": "Azure DevOps",
      "category": "Azure Boards",
      "subcategory": "Reporting",
      "id": "B04.01",
      "text": "Dashboard",
      "description": "Create Dashboard and PowerBI reports",
      "severity": "Medium",
      "waf": "Operations",
      "link": "https://learn.microsoft.com/azure/devops/report/dashboards/overview?view=azure-devops",
      "sourcePath": "checklists/ado_checklist.en.json",
      "sourceUrl": "https://github.com/Azure/review-checklists/blob/main/checklists/ado_checklist.en.json",
      "normalizedAt": "2026-05-08T18:00:27.107Z",
      "provenance": {
        "technology": "normalized",
        "technologyStatus": "normalized",
        "category": "source",
        "subcategory": "source",
        "severity": "normalized",
        "waf": "normalized",
        "service": "unavailable",
        "description": "source"
      }
    },
    {
      "guid": "a27a764a-90be-40e3-98ee-293c1bd363ca",
      "technology": "Azure DevOps",
      "technologySlug": "azure-devops-ado-checklist",
      "technologyStatus": "Preview",
      "technologyMaturityBucket": "Preview",
      "usageConfidence": "Medium",
      "technologyQualityScore": 89,
      "family": "Azure DevOps",
      "sourceKind": "checklists",
      "checklist": "Azure DevOps",
      "category": "Azure Boards",
      "subcategory": "Reporting",
      "id": "B04.02",
      "text": "Refine your backlog",
      "description": "Set up backlog",
      "severity": "Medium",
      "waf": "Operations",
      "link": "https://learn.microsoft.com/azure/devops/boards/backlogs/set-up-your-backlog?view=azure-devops",
      "sourcePath": "checklists/ado_checklist.en.json",
      "sourceUrl": "https://github.com/Azure/review-checklists/blob/main/checklists/ado_checklist.en.json",
      "normalizedAt": "2026-05-08T18:00:27.107Z",
      "provenance": {
        "technology": "normalized",
        "technologyStatus": "normalized",
        "category": "source",
        "subcategory": "source",
        "severity": "normalized",
        "waf": "normalized",
        "service": "unavailable",
        "description": "source"
      }
    },
    {
      "guid": "aab75719-49ab-4919-9dc9-fc9d1bb84b37",
      "technology": "Azure DevOps",
      "technologySlug": "azure-devops-ado-checklist",
      "technologyStatus": "Preview",
      "technologyMaturityBucket": "Preview",
      "usageConfidence": "Medium",
      "technologyQualityScore": 89,
      "family": "Azure DevOps",
      "sourceKind": "checklists",
      "checklist": "Azure DevOps",
      "category": "Azure Boards",
      "subcategory": "Reporting",
      "id": "B04.03",
      "text": "Visualize Relationships",
      "description": "Link your work items",
      "severity": "Medium",
      "waf": "Operations",
      "link": "https://learn.microsoft.com/azure/devops/boards/queries/link-work-items-support-traceability?view=azure-devops&tabs=browser",
      "sourcePath": "checklists/ado_checklist.en.json",
      "sourceUrl": "https://github.com/Azure/review-checklists/blob/main/checklists/ado_checklist.en.json",
      "normalizedAt": "2026-05-08T18:00:27.107Z",
      "provenance": {
        "technology": "normalized",
        "technologyStatus": "normalized",
        "category": "source",
        "subcategory": "source",
        "severity": "normalized",
        "waf": "normalized",
        "service": "unavailable",
        "description": "source"
      }
    },
    {
      "guid": "b5a67fcb-9ed5-4b35-978d-447a826c2863",
      "technology": "Azure DevOps",
      "technologySlug": "azure-devops-ado-checklist",
      "technologyStatus": "Preview",
      "technologyMaturityBucket": "Preview",
      "usageConfidence": "Medium",
      "technologyQualityScore": 89,
      "family": "Azure DevOps",
      "sourceKind": "checklists",
      "checklist": "Azure DevOps",
      "category": "Azure Pipelines",
      "subcategory": "Reporting",
      "id": "C01.01",
      "text": "Review Team Velocity",
      "description": "View the velocity report",
      "severity": "Low",
      "waf": "Operations",
      "link": "https://learn.microsoft.com/azure/devops/report/dashboards/team-velocity?view=azure-devops&tabs=in-context",
      "sourcePath": "checklists/ado_checklist.en.json",
      "sourceUrl": "https://github.com/Azure/review-checklists/blob/main/checklists/ado_checklist.en.json",
      "normalizedAt": "2026-05-08T18:00:27.107Z",
      "provenance": {
        "technology": "normalized",
        "technologyStatus": "normalized",
        "category": "source",
        "subcategory": "source",
        "severity": "normalized",
        "waf": "normalized",
        "service": "unavailable",
        "description": "source"
      }
    },
    {
      "guid": "c00f1cac-699e-4f1d-9a83-de5de36c1c81",
      "technology": "Azure DevOps",
      "technologySlug": "azure-devops-ado-checklist",
      "technologyStatus": "Preview",
      "technologyMaturityBucket": "Preview",
      "usageConfidence": "Medium",
      "technologyQualityScore": 89,
      "family": "Azure DevOps",
      "sourceKind": "checklists",
      "checklist": "Azure DevOps",
      "category": "Azure Pipelines",
      "subcategory": "Continuous Integration",
      "id": "C02.01",
      "text": "Set up pipeline",
      "description": "Create your first pipeline",
      "severity": "High",
      "waf": "Operations",
      "link": "https://learn.microsoft.com/azure/devops/pipelines/create-first-pipeline?view=azure-devops&tabs=java%2Ctfs-2018-2%2Cbrowser",
      "sourcePath": "checklists/ado_checklist.en.json",
      "sourceUrl": "https://github.com/Azure/review-checklists/blob/main/checklists/ado_checklist.en.json",
      "normalizedAt": "2026-05-08T18:00:27.107Z",
      "provenance": {
        "technology": "normalized",
        "technologyStatus": "normalized",
        "category": "source",
        "subcategory": "source",
        "severity": "normalized",
        "waf": "normalized",
        "service": "unavailable",
        "description": "source"
      }
    },
    {
      "guid": "870a0bc5-c1e4-43a1-a658-d2858ed67179",
      "technology": "Azure DevOps",
      "technologySlug": "azure-devops-ado-checklist",
      "technologyStatus": "Preview",
      "technologyMaturityBucket": "Preview",
      "usageConfidence": "Medium",
      "technologyQualityScore": 89,
      "family": "Azure DevOps",
      "sourceKind": "checklists",
      "checklist": "Azure DevOps",
      "category": "Azure Pipelines",
      "subcategory": "Continuous Integration",
      "id": "C02.02",
      "text": "Set Build triggers",
      "description": "Specify events that trigger pipelines",
      "severity": "High",
      "waf": "Operations",
      "link": "https://learn.microsoft.com/azure/devops/pipelines/build/triggers?view=azure-devops",
      "sourcePath": "checklists/ado_checklist.en.json",
      "sourceUrl": "https://github.com/Azure/review-checklists/blob/main/checklists/ado_checklist.en.json",
      "normalizedAt": "2026-05-08T18:00:27.107Z",
      "provenance": {
        "technology": "normalized",
        "technologyStatus": "normalized",
        "category": "source",
        "subcategory": "source",
        "severity": "normalized",
        "waf": "normalized",
        "service": "unavailable",
        "description": "source"
      }
    },
    {
      "guid": "b825546d-f2ae-4e45-93af-c8339248726d",
      "technology": "Azure DevOps",
      "technologySlug": "azure-devops-ado-checklist",
      "technologyStatus": "Preview",
      "technologyMaturityBucket": "Preview",
      "usageConfidence": "Medium",
      "technologyQualityScore": 89,
      "family": "Azure DevOps",
      "sourceKind": "checklists",
      "checklist": "Azure DevOps",
      "category": "Azure Pipelines",
      "subcategory": "Continuous Integration",
      "id": "C02.03",
      "text": "Customize YAML Pipeline",
      "description": "Use YAML to create build pipeline",
      "severity": "Low",
      "waf": "Operations",
      "link": "https://learn.microsoft.com/azure/devops/pipelines/customize-pipeline?view=azure-devops",
      "sourcePath": "checklists/ado_checklist.en.json",
      "sourceUrl": "https://github.com/Azure/review-checklists/blob/main/checklists/ado_checklist.en.json",
      "normalizedAt": "2026-05-08T18:00:27.107Z",
      "provenance": {
        "technology": "normalized",
        "technologyStatus": "normalized",
        "category": "source",
        "subcategory": "source",
        "severity": "normalized",
        "waf": "normalized",
        "service": "unavailable",
        "description": "source"
      }
    },
    {
      "guid": "d68c5b5c-2925-4394-a69b-9d379ac43bc6",
      "technology": "Azure DevOps",
      "technologySlug": "azure-devops-ado-checklist",
      "technologyStatus": "Preview",
      "technologyMaturityBucket": "Preview",
      "usageConfidence": "Medium",
      "technologyQualityScore": 89,
      "family": "Azure DevOps",
      "sourceKind": "checklists",
      "checklist": "Azure DevOps",
      "category": "Azure Pipelines",
      "subcategory": "Continuous Integration",
      "id": "C02.04",
      "text": "Use GUI for pipeline",
      "description": "Use classic GUI editor to set up pipeline",
      "severity": "Medium",
      "waf": "Operations",
      "link": "https://learn.microsoft.com/azure/devops/pipelines/get-started/pipelines-get-started?view=azure-devops&source=recommendations#define-pipelines-using-the-classic-interface",
      "sourcePath": "checklists/ado_checklist.en.json",
      "sourceUrl": "https://github.com/Azure/review-checklists/blob/main/checklists/ado_checklist.en.json",
      "normalizedAt": "2026-05-08T18:00:27.107Z",
      "provenance": {
        "technology": "normalized",
        "technologyStatus": "normalized",
        "category": "source",
        "subcategory": "source",
        "severity": "normalized",
        "waf": "normalized",
        "service": "unavailable",
        "description": "source"
      }
    },
    {
      "guid": "8d1d7665-7246-4b44-a564-b4dd74a759c7",
      "technology": "Azure DevOps",
      "technologySlug": "azure-devops-ado-checklist",
      "technologyStatus": "Preview",
      "technologyMaturityBucket": "Preview",
      "usageConfidence": "Medium",
      "technologyQualityScore": 89,
      "family": "Azure DevOps",
      "sourceKind": "checklists",
      "checklist": "Azure DevOps",
      "category": "Azure Pipelines",
      "subcategory": "Continuous Integration",
      "id": "C02.05",
      "text": "Configure Templates",
      "description": "Set up templates, parameters and expressions",
      "severity": "Medium",
      "waf": "Operations",
      "link": "https://learn.microsoft.com/azure/devops/pipelines/process/templates?view=azure-devops&pivots=templates-includes",
      "sourcePath": "checklists/ado_checklist.en.json",
      "sourceUrl": "https://github.com/Azure/review-checklists/blob/main/checklists/ado_checklist.en.json",
      "normalizedAt": "2026-05-08T18:00:27.107Z",
      "provenance": {
        "technology": "normalized",
        "technologyStatus": "normalized",
        "category": "source",
        "subcategory": "source",
        "severity": "normalized",
        "waf": "normalized",
        "service": "unavailable",
        "description": "source"
      }
    },
    {
      "guid": "633bd2a1-a27a-4764-a90b-e0e378ee293c",
      "technology": "Azure DevOps",
      "technologySlug": "azure-devops-ado-checklist",
      "technologyStatus": "Preview",
      "technologyMaturityBucket": "Preview",
      "usageConfidence": "Medium",
      "technologyQualityScore": 89,
      "family": "Azure DevOps",
      "sourceKind": "checklists",
      "checklist": "Azure DevOps",
      "category": "Azure Pipelines",
      "subcategory": "Continuous Integration",
      "id": "C02.06",
      "text": "Jobs",
      "description": "Set up jobs, stages and dependencies",
      "severity": "High",
      "waf": "Operations",
      "link": "https://learn.microsoft.com/azure/devops/pipelines/process/stages?view=azure-devops&tabs=yaml",
      "sourcePath": "checklists/ado_checklist.en.json",
      "sourceUrl": "https://github.com/Azure/review-checklists/blob/main/checklists/ado_checklist.en.json",
      "normalizedAt": "2026-05-08T18:00:27.107Z",
      "provenance": {
        "technology": "normalized",
        "technologyStatus": "normalized",
        "category": "source",
        "subcategory": "source",
        "severity": "normalized",
        "waf": "normalized",
        "service": "unavailable",
        "description": "source"
      }
    },
    {
      "guid": "1bd363ca-aab7-4571-a49a-b9193dc9fc9d",
      "technology": "Azure DevOps",
      "technologySlug": "azure-devops-ado-checklist",
      "technologyStatus": "Preview",
      "technologyMaturityBucket": "Preview",
      "usageConfidence": "Medium",
      "technologyQualityScore": 89,
      "family": "Azure DevOps",
      "sourceKind": "checklists",
      "checklist": "Azure DevOps",
      "category": "Azure Pipelines",
      "subcategory": "Continuous Integration",
      "id": "C02.07",
      "text": "Conditions and Demands",
      "description": "Set up conditions and Demands",
      "severity": "Medium",
      "waf": "Operations",
      "link": "https://learn.microsoft.com/azure/devops/pipelines/process/conditions?view=azure-devops&tabs=yaml%2Cstages",
      "sourcePath": "checklists/ado_checklist.en.json",
      "sourceUrl": "https://github.com/Azure/review-checklists/blob/main/checklists/ado_checklist.en.json",
      "normalizedAt": "2026-05-08T18:00:27.107Z",
      "provenance": {
        "technology": "normalized",
        "technologyStatus": "normalized",
        "category": "source",
        "subcategory": "source",
        "severity": "normalized",
        "waf": "normalized",
        "service": "unavailable",
        "description": "source"
      }
    },
    {
      "guid": "1bb84b37-b5a6-47fc-a9ed-5b35478d447a",
      "technology": "Azure DevOps",
      "technologySlug": "azure-devops-ado-checklist",
      "technologyStatus": "Preview",
      "technologyMaturityBucket": "Preview",
      "usageConfidence": "Medium",
      "technologyQualityScore": 89,
      "family": "Azure DevOps",
      "sourceKind": "checklists",
      "checklist": "Azure DevOps",
      "category": "Azure Pipelines",
      "subcategory": "Continuous Integration",
      "id": "C02.08",
      "text": "Variables",
      "description": "Define Variables",
      "severity": "High",
      "waf": "Operations",
      "link": "https://learn.microsoft.com/azure/devops/pipelines/process/variables?view=azure-devops&tabs=yaml%2Cbatch",
      "sourcePath": "checklists/ado_checklist.en.json",
      "sourceUrl": "https://github.com/Azure/review-checklists/blob/main/checklists/ado_checklist.en.json",
      "normalizedAt": "2026-05-08T18:00:27.107Z",
      "provenance": {
        "technology": "normalized",
        "technologyStatus": "normalized",
        "category": "source",
        "subcategory": "source",
        "severity": "normalized",
        "waf": "normalized",
        "service": "unavailable",
        "description": "source"
      }
    },
    {
      "guid": "826c2863-c00f-41ca-a699-ef1d5a83de5d",
      "technology": "Azure DevOps",
      "technologySlug": "azure-devops-ado-checklist",
      "technologyStatus": "Preview",
      "technologyMaturityBucket": "Preview",
      "usageConfidence": "Medium",
      "technologyQualityScore": 89,
      "family": "Azure DevOps",
      "sourceKind": "checklists",
      "checklist": "Azure DevOps",
      "category": "Azure Pipelines",
      "subcategory": "Continuous Deployment",
      "id": "C03.01",
      "text": "Deployment Pipeline",
      "description": "Set up your deployment pipeline",
      "severity": "High",
      "waf": "Operations",
      "link": "https://learn.microsoft.com/azure/devops/pipelines/process/create-multistage-pipeline?view=azure-devops",
      "sourcePath": "checklists/ado_checklist.en.json",
      "sourceUrl": "https://github.com/Azure/review-checklists/blob/main/checklists/ado_checklist.en.json",
      "normalizedAt": "2026-05-08T18:00:27.107Z",
      "provenance": {
        "technology": "normalized",
        "technologyStatus": "normalized",
        "category": "source",
        "subcategory": "source",
        "severity": "normalized",
        "waf": "normalized",
        "service": "unavailable",
        "description": "source"
      }
    },
    {
      "guid": "e36c1c81-870a-40bc-9c1e-43a18658d285",
      "technology": "Azure DevOps",
      "technologySlug": "azure-devops-ado-checklist",
      "technologyStatus": "Preview",
      "technologyMaturityBucket": "Preview",
      "usageConfidence": "Medium",
      "technologyQualityScore": 89,
      "family": "Azure DevOps",
      "sourceKind": "checklists",
      "checklist": "Azure DevOps",
      "category": "Azure Pipelines",
      "subcategory": "Continuous Deployment",
      "id": "C03.02",
      "text": "Release branch",
      "description": "Select correct branches to deploy from",
      "severity": "Medium",
      "waf": "Operations",
      "link": "https://learn.microsoft.com/azure/devops/pipelines/release/deploy-multiple-branches?view=azure-devops",
      "training": "https://learn.microsoft.com/azure/active-directory/managed-identities-azure-resources/overview",
      "sourcePath": "checklists/ado_checklist.en.json",
      "sourceUrl": "https://github.com/Azure/review-checklists/blob/main/checklists/ado_checklist.en.json",
      "normalizedAt": "2026-05-08T18:00:27.107Z",
      "provenance": {
        "technology": "normalized",
        "technologyStatus": "normalized",
        "category": "source",
        "subcategory": "source",
        "severity": "normalized",
        "waf": "normalized",
        "service": "unavailable",
        "description": "source"
      }
    },
    {
      "guid": "8ed67179-b825-4546-bf2a-ee4553afc833",
      "technology": "Azure DevOps",
      "technologySlug": "azure-devops-ado-checklist",
      "technologyStatus": "Preview",
      "technologyMaturityBucket": "Preview",
      "usageConfidence": "Medium",
      "technologyQualityScore": 89,
      "family": "Azure DevOps",
      "sourceKind": "checklists",
      "checklist": "Azure DevOps",
      "category": "Azure Pipelines",
      "subcategory": "Continuous Deployment",
      "id": "C03.03",
      "text": "Deploy to Azure",
      "description": "use relevant template to deploy to azure",
      "severity": "Medium",
      "waf": "Operations",
      "link": "https://learn.microsoft.com/azure/devops/pipelines/overview-azure?view=azure-devops",
      "sourcePath": "checklists/ado_checklist.en.json",
      "sourceUrl": "https://github.com/Azure/review-checklists/blob/main/checklists/ado_checklist.en.json",
      "normalizedAt": "2026-05-08T18:00:27.107Z",
      "provenance": {
        "technology": "normalized",
        "technologyStatus": "normalized",
        "category": "source",
        "subcategory": "source",
        "severity": "normalized",
        "waf": "normalized",
        "service": "unavailable",
        "description": "source"
      }
    },
    {
      "guid": "9248726d-d68c-45b5-a292-5394b69b9d37",
      "technology": "Azure DevOps",
      "technologySlug": "azure-devops-ado-checklist",
      "technologyStatus": "Preview",
      "technologyMaturityBucket": "Preview",
      "usageConfidence": "Medium",
      "technologyQualityScore": 89,
      "family": "Azure DevOps",
      "sourceKind": "checklists",
      "checklist": "Azure DevOps",
      "category": "Azure Pipelines",
      "subcategory": "Continuous Deployment",
      "id": "C03.04",
      "text": "Approvals and Checks",
      "description": "Define Release Approvals and pre deployment checks",
      "severity": "Medium",
      "waf": "Operations",
      "link": "https://learn.microsoft.com/azure/devops/pipelines/process/approvals?view=azure-devops&tabs=check-pass",
      "training": "https://learn.microsoft.com/learn/modules/azure-ad-privileged-identity-management/",
      "sourcePath": "checklists/ado_checklist.en.json",
      "sourceUrl": "https://github.com/Azure/review-checklists/blob/main/checklists/ado_checklist.en.json",
      "normalizedAt": "2026-05-08T18:00:27.107Z",
      "provenance": {
        "technology": "normalized",
        "technologyStatus": "normalized",
        "category": "source",
        "subcategory": "source",
        "severity": "normalized",
        "waf": "normalized",
        "service": "unavailable",
        "description": "source"
      }
    },
    {
      "guid": "9ac43bc6-8d1d-4766-9724-6b448564b4dd",
      "technology": "Azure DevOps",
      "technologySlug": "azure-devops-ado-checklist",
      "technologyStatus": "Preview",
      "technologyMaturityBucket": "Preview",
      "usageConfidence": "Medium",
      "technologyQualityScore": 89,
      "family": "Azure DevOps",
      "sourceKind": "checklists",
      "checklist": "Azure DevOps",
      "category": "Azure Pipelines",
      "subcategory": "Continuous Deployment",
      "id": "C03.05",
      "text": "Gates",
      "description": "Define Gates and post deployment checks",
      "severity": "Medium",
      "waf": "Operations",
      "link": "https://learn.microsoft.com/azure/devops/pipelines/release/approvals/?view=azure-devops&tabs=yaml",
      "sourcePath": "checklists/ado_checklist.en.json",
      "sourceUrl": "https://github.com/Azure/review-checklists/blob/main/checklists/ado_checklist.en.json",
      "normalizedAt": "2026-05-08T18:00:27.107Z",
      "provenance": {
        "technology": "normalized",
        "technologyStatus": "normalized",
        "category": "source",
        "subcategory": "source",
        "severity": "normalized",
        "waf": "normalized",
        "service": "unavailable",
        "description": "source"
      }
    },
    {
      "guid": "74a759c7-633b-4d2a-8a27-a764a90be0e3",
      "technology": "Azure DevOps",
      "technologySlug": "azure-devops-ado-checklist",
      "technologyStatus": "Preview",
      "technologyMaturityBucket": "Preview",
      "usageConfidence": "Medium",
      "technologyQualityScore": 89,
      "family": "Azure DevOps",
      "sourceKind": "checklists",
      "checklist": "Azure DevOps",
      "category": "Azure Pipelines",
      "subcategory": "Continuous Deployment",
      "id": "C03.06",
      "text": "Azure Function Checks",
      "description": "Define Azure Function and REST API Checks",
      "severity": "Low",
      "waf": "Operations",
      "link": "https://learn.microsoft.com/azure/devops/pipelines/process/invoke-checks?view=azure-devops",
      "training": "https://learn.microsoft.com/learn/paths/implement-resource-mgmt-security/",
      "sourcePath": "checklists/ado_checklist.en.json",
      "sourceUrl": "https://github.com/Azure/review-checklists/blob/main/checklists/ado_checklist.en.json",
      "normalizedAt": "2026-05-08T18:00:27.107Z",
      "provenance": {
        "technology": "normalized",
        "technologyStatus": "normalized",
        "category": "source",
        "subcategory": "source",
        "severity": "normalized",
        "waf": "normalized",
        "service": "unavailable",
        "description": "source"
      }
    },
    {
      "guid": "78ee293c-1bd3-463c-aaab-7571949ab919",
      "technology": "Azure DevOps",
      "technologySlug": "azure-devops-ado-checklist",
      "technologyStatus": "Preview",
      "technologyMaturityBucket": "Preview",
      "usageConfidence": "Medium",
      "technologyQualityScore": 89,
      "family": "Azure DevOps",
      "sourceKind": "checklists",
      "checklist": "Azure DevOps",
      "category": "Azure Pipelines",
      "subcategory": "Continuous Deployment",
      "id": "C03.07",
      "text": "Pipline Reports",
      "description": "Review pipeline reports",
      "severity": "High",
      "waf": "Operations",
      "link": "https://learn.microsoft.com/azure/devops/pipelines/reports/pipelinereport?view=azure-devops",
      "training": "https://learn.microsoft.com/learn/modules/plan-implement-administer-conditional-access/",
      "sourcePath": "checklists/ado_checklist.en.json",
      "sourceUrl": "https://github.com/Azure/review-checklists/blob/main/checklists/ado_checklist.en.json",
      "normalizedAt": "2026-05-08T18:00:27.107Z",
      "provenance": {
        "technology": "normalized",
        "technologyStatus": "normalized",
        "category": "source",
        "subcategory": "source",
        "severity": "normalized",
        "waf": "normalized",
        "service": "unavailable",
        "description": "source"
      }
    },
    {
      "guid": "3dc9fc9d-1bb8-44b3-9b5a-67fcb9ed5b35",
      "technology": "Azure DevOps",
      "technologySlug": "azure-devops-ado-checklist",
      "technologyStatus": "Preview",
      "technologyMaturityBucket": "Preview",
      "usageConfidence": "Medium",
      "technologyQualityScore": 89,
      "family": "Azure DevOps",
      "sourceKind": "checklists",
      "checklist": "Azure DevOps",
      "category": "Azure Pipelines",
      "subcategory": "Analytics",
      "id": "C04.01",
      "text": "Pipeline Result Trend",
      "description": "configure Trend Result widget",
      "severity": "Medium",
      "waf": "Operations",
      "link": "https://learn.microsoft.com/azure/devops/report/dashboards/analytics-widgets?toc=%2Fazure%2Fdevops%2Fpipelines%2Ftoc.json&view=azure-devops#test-results-trend-advanced",
      "training": "https://learn.microsoft.com/learn/modules/secure-aad-users-with-mfa/",
      "sourcePath": "checklists/ado_checklist.en.json",
      "sourceUrl": "https://github.com/Azure/review-checklists/blob/main/checklists/ado_checklist.en.json",
      "normalizedAt": "2026-05-08T18:00:27.107Z",
      "provenance": {
        "technology": "normalized",
        "technologyStatus": "normalized",
        "category": "source",
        "subcategory": "source",
        "severity": "normalized",
        "waf": "normalized",
        "service": "unavailable",
        "description": "source"
      }
    },
    {
      "guid": "478d447a-826c-4286-9c00-f1cac699ef1d",
      "technology": "Azure DevOps",
      "technologySlug": "azure-devops-ado-checklist",
      "technologyStatus": "Preview",
      "technologyMaturityBucket": "Preview",
      "usageConfidence": "Medium",
      "technologyQualityScore": 89,
      "family": "Azure DevOps",
      "sourceKind": "checklists",
      "checklist": "Azure DevOps",
      "category": "Azure Pipelines",
      "subcategory": "Analytics",
      "id": "C04.02",
      "text": "Work Tracking with Pipeline",
      "description": "Connect with WIT to visualize work",
      "severity": "Medium",
      "waf": "Operations",
      "link": "https://learn.microsoft.com/azure/devops/pipelines/integrations/configure-pipelines-work-tracking?view=azure-devops&tabs=yaml",
      "training": "https://learn.microsoft.com/learn/paths/azure-administrator-manage-identities-governance/",
      "sourcePath": "checklists/ado_checklist.en.json",
      "sourceUrl": "https://github.com/Azure/review-checklists/blob/main/checklists/ado_checklist.en.json",
      "normalizedAt": "2026-05-08T18:00:27.107Z",
      "provenance": {
        "technology": "normalized",
        "technologyStatus": "normalized",
        "category": "source",
        "subcategory": "source",
        "severity": "normalized",
        "waf": "normalized",
        "service": "unavailable",
        "description": "source"
      }
    },
    {
      "guid": "5a83de5d-e36c-41c8-8870-a0bc5c1e43a1",
      "technology": "Azure DevOps",
      "technologySlug": "azure-devops-ado-checklist",
      "technologyStatus": "Preview",
      "technologyMaturityBucket": "Preview",
      "usageConfidence": "Medium",
      "technologyQualityScore": 89,
      "family": "Azure DevOps",
      "sourceKind": "checklists",
      "checklist": "Azure DevOps",
      "category": "Azure Pipelines",
      "subcategory": "Continuous Deployment",
      "id": "C05.01",
      "text": "Agents and agent pools",
      "description": "Understand agent pools",
      "severity": "Medium",
      "waf": "Operations",
      "link": "https://learn.microsoft.com/azure/devops/pipelines/agents/agents?view=azure-devops&tabs=yaml%2Cbrowser",
      "training": "https://learn.microsoft.com/learn/modules/azure-ad-privileged-identity-management/",
      "sourcePath": "checklists/ado_checklist.en.json",
      "sourceUrl": "https://github.com/Azure/review-checklists/blob/main/checklists/ado_checklist.en.json",
      "normalizedAt": "2026-05-08T18:00:27.107Z",
      "provenance": {
        "technology": "normalized",
        "technologyStatus": "normalized",
        "category": "source",
        "subcategory": "source",
        "severity": "normalized",
        "waf": "normalized",
        "service": "unavailable",
        "description": "source"
      }
    },
    {
      "guid": "8658d285-8ed6-4717-ab82-5546df2aee45",
      "technology": "Azure DevOps",
      "technologySlug": "azure-devops-ado-checklist",
      "technologyStatus": "Preview",
      "technologyMaturityBucket": "Preview",
      "usageConfidence": "Medium",
      "technologyQualityScore": 89,
      "family": "Azure DevOps",
      "sourceKind": "checklists",
      "checklist": "Azure DevOps",
      "category": "Azure Pipelines",
      "subcategory": "Continuous Deployment",
      "id": "C05.02",
      "text": "Deployment Groups",
      "description": "Understand and provision Deployment Groups when required",
      "severity": "Low",
      "waf": "Operations",
      "link": "https://learn.microsoft.com/azure/devops/pipelines/release/deployment-groups/?view=azure-devops",
      "training": "https://learn.microsoft.com/learn/modules/explore-basic-services-identity-types/",
      "sourcePath": "checklists/ado_checklist.en.json",
      "sourceUrl": "https://github.com/Azure/review-checklists/blob/main/checklists/ado_checklist.en.json",
      "normalizedAt": "2026-05-08T18:00:27.107Z",
      "provenance": {
        "technology": "normalized",
        "technologyStatus": "normalized",
        "category": "source",
        "subcategory": "source",
        "severity": "normalized",
        "waf": "normalized",
        "service": "unavailable",
        "description": "source"
      }
    },
    {
      "guid": "53afc833-9248-4726-bd68-c5b5c2925394",
      "technology": "Azure DevOps",
      "technologySlug": "azure-devops-ado-checklist",
      "technologyStatus": "Preview",
      "technologyMaturityBucket": "Preview",
      "usageConfidence": "Medium",
      "technologyQualityScore": 89,
      "family": "Azure DevOps",
      "sourceKind": "checklists",
      "checklist": "Azure DevOps",
      "category": "Azure Pipelines",
      "subcategory": "Continuous Deployment",
      "id": "C05.03",
      "text": "Deploy to Kubernetes",
      "description": "Understand Kubernetes Deployment",
      "severity": "Low",
      "waf": "Operations",
      "link": "https://learn.microsoft.com/azure/devops/pipelines/ecosystems/kubernetes/deploy?view=azure-devops",
      "training": "https://learn.microsoft.com/learn/paths/manage-identity-and-access/",
      "sourcePath": "checklists/ado_checklist.en.json",
      "sourceUrl": "https://github.com/Azure/review-checklists/blob/main/checklists/ado_checklist.en.json",
      "normalizedAt": "2026-05-08T18:00:27.107Z",
      "provenance": {
        "technology": "normalized",
        "technologyStatus": "normalized",
        "category": "source",
        "subcategory": "source",
        "severity": "normalized",
        "waf": "normalized",
        "service": "unavailable",
        "description": "source"
      }
    },
    {
      "guid": "b69b9d37-9ac4-43bc-98d1-d76657246b44",
      "technology": "Azure DevOps",
      "technologySlug": "azure-devops-ado-checklist",
      "technologyStatus": "Preview",
      "technologyMaturityBucket": "Preview",
      "usageConfidence": "Medium",
      "technologyQualityScore": 89,
      "family": "Azure DevOps",
      "sourceKind": "checklists",
      "checklist": "Azure DevOps",
      "category": "Azure Pipelines",
      "subcategory": "Security",
      "id": "C06.01",
      "text": "DAST Scan",
      "description": "Perform Dynamic Security Testing",
      "severity": "Medium",
      "waf": "Security",
      "link": "https://devblogs.microsoft.com/premier-developer/azure-devops-pipelines-leveraging-owasp-zap-in-the-release-pipeline/",
      "training": "https://learn.microsoft.com/learn/modules/create-custom-azure-roles-with-rbac/",
      "sourcePath": "checklists/ado_checklist.en.json",
      "sourceUrl": "https://github.com/Azure/review-checklists/blob/main/checklists/ado_checklist.en.json",
      "normalizedAt": "2026-05-08T18:00:27.107Z",
      "provenance": {
        "technology": "normalized",
        "technologyStatus": "normalized",
        "category": "source",
        "subcategory": "source",
        "severity": "normalized",
        "waf": "normalized",
        "service": "unavailable",
        "description": "source"
      }
    },
    {
      "guid": "8564b4dd-74a7-459c-9633-bd2a1a27a764",
      "technology": "Azure DevOps",
      "technologySlug": "azure-devops-ado-checklist",
      "technologyStatus": "Preview",
      "technologyMaturityBucket": "Preview",
      "usageConfidence": "Medium",
      "technologyQualityScore": 89,
      "family": "Azure DevOps",
      "sourceKind": "checklists",
      "checklist": "Azure DevOps",
      "category": "Azure Pipelines",
      "subcategory": "Security",
      "id": "C06.02",
      "text": "Service Connections",
      "description": "Manage Service Connections",
      "severity": "Medium",
      "waf": "Security",
      "link": "https://learn.microsoft.com/azure/devops/pipelines/library/service-endpoints?view=azure-devops&tabs=yaml",
      "training": "https://learn.microsoft.com/learn/paths/secure-your-cloud-data/",
      "sourcePath": "checklists/ado_checklist.en.json",
      "sourceUrl": "https://github.com/Azure/review-checklists/blob/main/checklists/ado_checklist.en.json",
      "normalizedAt": "2026-05-08T18:00:27.107Z",
      "provenance": {
        "technology": "normalized",
        "technologyStatus": "normalized",
        "category": "source",
        "subcategory": "source",
        "severity": "normalized",
        "waf": "normalized",
        "service": "unavailable",
        "description": "source"
      }
    },
    {
      "guid": "a90be0e3-78ee-4293-a1bd-363caaab7571",
      "technology": "Azure DevOps",
      "technologySlug": "azure-devops-ado-checklist",
      "technologyStatus": "Preview",
      "technologyMaturityBucket": "Preview",
      "usageConfidence": "Medium",
      "technologyQualityScore": 89,
      "family": "Azure DevOps",
      "sourceKind": "checklists",
      "checklist": "Azure DevOps",
      "category": "Azure Pipelines",
      "subcategory": "Security",
      "id": "C06.03",
      "text": "Retention Policies",
      "description": "Set data retention policies for CI and CD",
      "severity": "Medium",
      "waf": "Security",
      "link": "https://learn.microsoft.com/azure/devops/pipelines/policies/retention?view=azure-devops&tabs=yaml",
      "training": "https://learn.microsoft.com/learn/modules/azure-active-directory/",
      "sourcePath": "checklists/ado_checklist.en.json",
      "sourceUrl": "https://github.com/Azure/review-checklists/blob/main/checklists/ado_checklist.en.json",
      "normalizedAt": "2026-05-08T18:00:27.107Z",
      "provenance": {
        "technology": "normalized",
        "technologyStatus": "normalized",
        "category": "source",
        "subcategory": "source",
        "severity": "normalized",
        "waf": "normalized",
        "service": "unavailable",
        "description": "source"
      }
    },
    {
      "guid": "949ab919-3dc9-4fc9-b1bb-84b37b5a67fc",
      "technology": "Azure DevOps",
      "technologySlug": "azure-devops-ado-checklist",
      "technologyStatus": "Preview",
      "technologyMaturityBucket": "Preview",
      "usageConfidence": "Medium",
      "technologyQualityScore": 89,
      "family": "Azure DevOps",
      "sourceKind": "checklists",
      "checklist": "Azure DevOps",
      "category": "Azure Pipelines",
      "subcategory": "Administration",
      "id": "C07.01",
      "text": "Parallel Pipelines",
      "description": "Set up and pay for concurrent pipelines",
      "severity": "Low",
      "waf": "Operations",
      "link": "https://learn.microsoft.com/azure/devops/pipelines/licensing/concurrent-jobs?view=azure-devops&tabs=ms-hosted",
      "training": "https://learn.microsoft.com/learn/modules/implement-hybrid-identity-windows-server/",
      "sourcePath": "checklists/ado_checklist.en.json",
      "sourceUrl": "https://github.com/Azure/review-checklists/blob/main/checklists/ado_checklist.en.json",
      "normalizedAt": "2026-05-08T18:00:27.107Z",
      "provenance": {
        "technology": "normalized",
        "technologyStatus": "normalized",
        "category": "source",
        "subcategory": "source",
        "severity": "normalized",
        "waf": "normalized",
        "service": "unavailable",
        "description": "source"
      }
    },
    {
      "guid": "b9ed5b35-478d-4447-a826-c2863c00f1ca",
      "technology": "Azure DevOps",
      "technologySlug": "azure-devops-ado-checklist",
      "technologyStatus": "Preview",
      "technologyMaturityBucket": "Preview",
      "usageConfidence": "Medium",
      "technologyQualityScore": 89,
      "family": "Azure DevOps",
      "sourceKind": "checklists",
      "checklist": "Azure DevOps",
      "category": "Azure Pipelines",
      "subcategory": "Security",
      "id": "C08.01",
      "text": "Pipeline Permissions",
      "description": "Set pipeline permissions",
      "severity": "Medium",
      "waf": "Security",
      "link": "https://learn.microsoft.com/azure/devops/pipelines/policies/permissions?view=azure-devops",
      "training": "https://learn.microsoft.com/learn/paths/implement-windows-server-iaas-virtual-machine-identity/",
      "sourcePath": "checklists/ado_checklist.en.json",
      "sourceUrl": "https://github.com/Azure/review-checklists/blob/main/checklists/ado_checklist.en.json",
      "normalizedAt": "2026-05-08T18:00:27.107Z",
      "provenance": {
        "technology": "normalized",
        "technologyStatus": "normalized",
        "category": "source",
        "subcategory": "source",
        "severity": "normalized",
        "waf": "normalized",
        "service": "unavailable",
        "description": "source"
      }
    },
    {
      "guid": "c699ef1d-5a83-4de5-be36-c1c81870a0bc",
      "technology": "Azure DevOps",
      "technologySlug": "azure-devops-ado-checklist",
      "technologyStatus": "Preview",
      "technologyMaturityBucket": "Preview",
      "usageConfidence": "Medium",
      "technologyQualityScore": 89,
      "family": "Azure DevOps",
      "sourceKind": "checklists",
      "checklist": "Azure DevOps",
      "category": "Azure Pipelines",
      "subcategory": "Security",
      "id": "C08.02",
      "text": "Pipeline Users",
      "description": "Add users to pipeline",
      "severity": "Low",
      "waf": "Security",
      "link": "https://learn.microsoft.com/azure/devops/pipelines/policies/set-permissions?view=azure-devops",
      "training": "https://learn.microsoft.com/learn/paths/implement-applications-external-access-azure-ad/",
      "sourcePath": "checklists/ado_checklist.en.json",
      "sourceUrl": "https://github.com/Azure/review-checklists/blob/main/checklists/ado_checklist.en.json",
      "normalizedAt": "2026-05-08T18:00:27.107Z",
      "provenance": {
        "technology": "normalized",
        "technologyStatus": "normalized",
        "category": "source",
        "subcategory": "source",
        "severity": "normalized",
        "waf": "normalized",
        "service": "unavailable",
        "description": "source"
      }
    },
    {
      "guid": "5c1e43a1-8658-4d28-98ed-67179b825546",
      "technology": "Azure DevOps",
      "technologySlug": "azure-devops-ado-checklist",
      "technologyStatus": "Preview",
      "technologyMaturityBucket": "Preview",
      "usageConfidence": "Medium",
      "technologyQualityScore": 89,
      "family": "Azure DevOps",
      "sourceKind": "checklists",
      "checklist": "Azure DevOps",
      "category": "Azure Artifact",
      "subcategory": "Configuration",
      "id": "D01.01",
      "text": "Artifact In Pipeline",
      "description": "Configure Artifacts",
      "severity": "Medium",
      "waf": "Operations",
      "link": "https://learn.microsoft.com/azure/devops/pipelines/artifacts/artifacts-overview?view=azure-devops&tabs=nuget",
      "training": "https://learn.microsoft.com/learn/modules/design-identity-security-strategy/",
      "sourcePath": "checklists/ado_checklist.en.json",
      "sourceUrl": "https://github.com/Azure/review-checklists/blob/main/checklists/ado_checklist.en.json",
      "normalizedAt": "2026-05-08T18:00:27.107Z",
      "provenance": {
        "technology": "normalized",
        "technologyStatus": "normalized",
        "category": "source",
        "subcategory": "source",
        "severity": "normalized",
        "waf": "normalized",
        "service": "unavailable",
        "description": "source"
      }
    },
    {
      "guid": "df2aee45-53af-4c83-9924-8726dd68c5b5",
      "technology": "Azure DevOps",
      "technologySlug": "azure-devops-ado-checklist",
      "technologyStatus": "Preview",
      "technologyMaturityBucket": "Preview",
      "usageConfidence": "Medium",
      "technologyQualityScore": 89,
      "family": "Azure DevOps",
      "sourceKind": "checklists",
      "checklist": "Azure DevOps",
      "category": "Azure Artifact",
      "subcategory": "Configuration",
      "id": "D01.02",
      "text": "Publish and download Artifact",
      "description": "Publish and consume artifact in pipeline",
      "severity": "Medium",
      "waf": "Operations",
      "link": "https://learn.microsoft.com/azure/devops/pipelines/artifacts/pipeline-artifacts?view=azure-devops&tabs=yaml",
      "training": "https://learn.microsoft.com/azure/architecture/example-scenario/identity/adds-extend-domain",
      "sourcePath": "checklists/ado_checklist.en.json",
      "sourceUrl": "https://github.com/Azure/review-checklists/blob/main/checklists/ado_checklist.en.json",
      "normalizedAt": "2026-05-08T18:00:27.107Z",
      "provenance": {
        "technology": "normalized",
        "technologyStatus": "normalized",
        "category": "source",
        "subcategory": "source",
        "severity": "normalized",
        "waf": "normalized",
        "service": "unavailable",
        "description": "source"
      }
    },
    {
      "guid": "c2925394-b69b-49d3-99ac-43bc68d1d766",
      "technology": "Azure DevOps",
      "technologySlug": "azure-devops-ado-checklist",
      "technologyStatus": "Preview",
      "technologyMaturityBucket": "Preview",
      "usageConfidence": "Medium",
      "technologyQualityScore": 89,
      "family": "Azure DevOps",
      "sourceKind": "checklists",
      "checklist": "Azure DevOps",
      "category": "Azure Artifact",
      "subcategory": "Configuration",
      "id": "D01.03",
      "text": "NuGet",
      "description": "Publish NuGet packages with artifacts",
      "severity": "Low",
      "waf": "Operations",
      "link": "https://learn.microsoft.com/azure/devops/pipelines/artifacts/nuget?view=azure-devops&tabs=yaml",
      "training": "https://learn.microsoft.com/azure/role-based-access-control/overview",
      "sourcePath": "checklists/ado_checklist.en.json",
      "sourceUrl": "https://github.com/Azure/review-checklists/blob/main/checklists/ado_checklist.en.json",
      "normalizedAt": "2026-05-08T18:00:27.107Z",
      "provenance": {
        "technology": "normalized",
        "technologyStatus": "normalized",
        "category": "source",
        "subcategory": "source",
        "severity": "normalized",
        "waf": "normalized",
        "service": "unavailable",
        "description": "source"
      }
    },
    {
      "guid": "57246b44-8564-4b4d-b74a-759c7633bd2a",
      "technology": "Azure DevOps",
      "technologySlug": "azure-devops-ado-checklist",
      "technologyStatus": "Preview",
      "technologyMaturityBucket": "Preview",
      "usageConfidence": "Medium",
      "technologyQualityScore": 89,
      "family": "Azure DevOps",
      "sourceKind": "checklists",
      "checklist": "Azure DevOps",
      "category": "Azure Artifact",
      "subcategory": "Configuration",
      "id": "D01.04",
      "text": "Maven",
      "description": "Publish Maven packages with artifacts",
      "severity": "Low",
      "waf": "Operations",
      "link": "https://learn.microsoft.com/azure/devops/pipelines/artifacts/publish-maven-artifacts?view=azure-devops",
      "sourcePath": "checklists/ado_checklist.en.json",
      "sourceUrl": "https://github.com/Azure/review-checklists/blob/main/checklists/ado_checklist.en.json",
      "normalizedAt": "2026-05-08T18:00:27.107Z",
      "provenance": {
        "technology": "normalized",
        "technologyStatus": "normalized",
        "category": "source",
        "subcategory": "source",
        "severity": "normalized",
        "waf": "normalized",
        "service": "unavailable",
        "description": "source"
      }
    },
    {
      "guid": "1a27a764-a90b-4e0e-978e-e293c1bd363c",
      "technology": "Azure DevOps",
      "technologySlug": "azure-devops-ado-checklist",
      "technologyStatus": "Preview",
      "technologyMaturityBucket": "Preview",
      "usageConfidence": "Medium",
      "technologyQualityScore": 89,
      "family": "Azure DevOps",
      "sourceKind": "checklists",
      "checklist": "Azure DevOps",
      "category": "Azure Artifact",
      "subcategory": "Configuration",
      "id": "D01.05",
      "text": "NPM",
      "description": "Publish NPM packages with artifacts",
      "severity": "Low",
      "waf": "Operations",
      "link": "https://learn.microsoft.com/azure/devops/pipelines/artifacts/npm?view=azure-devops&tabs=yaml",
      "sourcePath": "checklists/ado_checklist.en.json",
      "sourceUrl": "https://github.com/Azure/review-checklists/blob/main/checklists/ado_checklist.en.json",
      "normalizedAt": "2026-05-08T18:00:27.107Z",
      "provenance": {
        "technology": "normalized",
        "technologyStatus": "normalized",
        "category": "source",
        "subcategory": "source",
        "severity": "normalized",
        "waf": "normalized",
        "service": "unavailable",
        "description": "source"
      }
    },
    {
      "guid": "aaab7571-949a-4b91-a3dc-9fc9d1bb84b3",
      "technology": "Azure DevOps",
      "technologySlug": "azure-devops-ado-checklist",
      "technologyStatus": "Preview",
      "technologyMaturityBucket": "Preview",
      "usageConfidence": "Medium",
      "technologyQualityScore": 89,
      "family": "Azure DevOps",
      "sourceKind": "checklists",
      "checklist": "Azure DevOps",
      "category": "Azure Artifact",
      "subcategory": "Configuration",
      "id": "D01.06",
      "text": "Best Practices",
      "description": "Best Practices to work with Azure Artifact",
      "severity": "Medium",
      "waf": "Operations",
      "link": "https://learn.microsoft.com/azure/devops/artifacts/concepts/best-practices?view=azure-devops",
      "sourcePath": "checklists/ado_checklist.en.json",
      "sourceUrl": "https://github.com/Azure/review-checklists/blob/main/checklists/ado_checklist.en.json",
      "normalizedAt": "2026-05-08T18:00:27.107Z",
      "provenance": {
        "technology": "normalized",
        "technologyStatus": "normalized",
        "category": "source",
        "subcategory": "source",
        "severity": "normalized",
        "waf": "normalized",
        "service": "unavailable",
        "description": "source"
      }
    },
    {
      "guid": "7b5a67fc-b9ed-45b3-9478-d447a826c286",
      "technology": "Azure DevOps",
      "technologySlug": "azure-devops-ado-checklist",
      "technologyStatus": "Preview",
      "technologyMaturityBucket": "Preview",
      "usageConfidence": "Medium",
      "technologyQualityScore": 89,
      "family": "Azure DevOps",
      "sourceKind": "checklists",
      "checklist": "Azure DevOps",
      "category": "DevOps Practice",
      "subcategory": "Practice",
      "id": "E01.01",
      "text": "What to monitor?",
      "description": "What is monitoring?",
      "severity": "High",
      "waf": "Operations",
      "link": "https://learn.microsoft.com/devops/operate/what-is-monitoring",
      "sourcePath": "checklists/ado_checklist.en.json",
      "sourceUrl": "https://github.com/Azure/review-checklists/blob/main/checklists/ado_checklist.en.json",
      "normalizedAt": "2026-05-08T18:00:27.107Z",
      "provenance": {
        "technology": "normalized",
        "technologyStatus": "normalized",
        "category": "source",
        "subcategory": "source",
        "severity": "normalized",
        "waf": "normalized",
        "service": "unavailable",
        "description": "source"
      }
    },
    {
      "guid": "3c00f1ca-c699-4ef1-b5a8-3de5de36c1c8",
      "technology": "Azure DevOps",
      "technologySlug": "azure-devops-ado-checklist",
      "technologyStatus": "Preview",
      "technologyMaturityBucket": "Preview",
      "usageConfidence": "Medium",
      "technologyQualityScore": 89,
      "family": "Azure DevOps",
      "sourceKind": "checklists",
      "checklist": "Azure DevOps",
      "category": "DevOps Practice",
      "subcategory": "Practice",
      "id": "E01.02",
      "text": "Safe Deployment Practices",
      "description": "Progressive Exposure Strategy",
      "severity": "Medium",
      "waf": "Operations",
      "link": "https://learn.microsoft.com/devops/operate/safe-deployment-practices",
      "sourcePath": "checklists/ado_checklist.en.json",
      "sourceUrl": "https://github.com/Azure/review-checklists/blob/main/checklists/ado_checklist.en.json",
      "normalizedAt": "2026-05-08T18:00:27.107Z",
      "provenance": {
        "technology": "normalized",
        "technologyStatus": "normalized",
        "category": "source",
        "subcategory": "source",
        "severity": "normalized",
        "waf": "normalized",
        "service": "unavailable",
        "description": "source"
      }
    },
    {
      "guid": "1870a0bc-5c1e-443a-8865-8d2858ed6717",
      "technology": "Azure DevOps",
      "technologySlug": "azure-devops-ado-checklist",
      "technologyStatus": "Preview",
      "technologyMaturityBucket": "Preview",
      "usageConfidence": "Medium",
      "technologyQualityScore": 89,
      "family": "Azure DevOps",
      "sourceKind": "checklists",
      "checklist": "Azure DevOps",
      "category": "DevOps Practice",
      "subcategory": "Practice",
      "id": "E01.03",
      "text": "Case Study",
      "description": "Microsoft runs reliable systems with DevOps",
      "severity": "Low",
      "waf": "Operations",
      "link": "https://learn.microsoft.com/devops/operate/how-microsoft-operates-devops",
      "training": "https://learn.microsoft.com/azure/azure-monitor/logs/design-logs-deployment",
      "sourcePath": "checklists/ado_checklist.en.json",
      "sourceUrl": "https://github.com/Azure/review-checklists/blob/main/checklists/ado_checklist.en.json",
      "normalizedAt": "2026-05-08T18:00:27.107Z",
      "provenance": {
        "technology": "normalized",
        "technologyStatus": "normalized",
        "category": "source",
        "subcategory": "source",
        "severity": "normalized",
        "waf": "normalized",
        "service": "unavailable",
        "description": "source"
      }
    },
    {
      "guid": "9b825546-df2a-4ee4-953a-fc8339248726",
      "technology": "Azure DevOps",
      "technologySlug": "azure-devops-ado-checklist",
      "technologyStatus": "Preview",
      "technologyMaturityBucket": "Preview",
      "usageConfidence": "Medium",
      "technologyQualityScore": 89,
      "family": "Azure DevOps",
      "sourceKind": "checklists",
      "checklist": "Azure DevOps",
      "category": "DevOps Practice",
      "subcategory": "Practice",
      "id": "E01.04",
      "text": "DevSecOps",
      "description": "Security in DevOps",
      "severity": "Medium",
      "waf": "Security",
      "link": "https://learn.microsoft.com/devops/operate/security-in-devops",
      "sourcePath": "checklists/ado_checklist.en.json",
      "sourceUrl": "https://github.com/Azure/review-checklists/blob/main/checklists/ado_checklist.en.json",
      "normalizedAt": "2026-05-08T18:00:27.107Z",
      "provenance": {
        "technology": "normalized",
        "technologyStatus": "normalized",
        "category": "source",
        "subcategory": "source",
        "severity": "normalized",
        "waf": "normalized",
        "service": "unavailable",
        "description": "source"
      }
    },
    {
      "guid": "dd68c5b5-c292-4539-9b69-b9d379ac43bc",
      "technology": "Azure DevOps",
      "technologySlug": "azure-devops-ado-checklist",
      "technologyStatus": "Preview",
      "technologyMaturityBucket": "Preview",
      "usageConfidence": "Medium",
      "technologyQualityScore": 89,
      "family": "Azure DevOps",
      "sourceKind": "checklists",
      "checklist": "Azure DevOps",
      "category": "DevOps Practice",
      "subcategory": "Practice",
      "id": "E01.05",
      "text": "DevSecops",
      "description": "Enable DevSecops with Azure And GitHub",
      "severity": "Low",
      "waf": "Security",
      "link": "https://learn.microsoft.com/devops/devsecops/enable-devsecops-azure-github",
      "training": "https://learn.microsoft.com/learn/paths/architect-infrastructure-operations/",
      "sourcePath": "checklists/ado_checklist.en.json",
      "sourceUrl": "https://github.com/Azure/review-checklists/blob/main/checklists/ado_checklist.en.json",
      "normalizedAt": "2026-05-08T18:00:27.107Z",
      "provenance": {
        "technology": "normalized",
        "technologyStatus": "normalized",
        "category": "source",
        "subcategory": "source",
        "severity": "normalized",
        "waf": "normalized",
        "service": "unavailable",
        "description": "source"
      }
    },
    {
      "guid": "68d1d766-5724-46b4-9856-4b4dd74a759c",
      "technology": "Azure DevOps",
      "technologySlug": "azure-devops-ado-checklist",
      "technologyStatus": "Preview",
      "technologyMaturityBucket": "Preview",
      "usageConfidence": "Medium",
      "technologyQualityScore": 89,
      "family": "Azure DevOps",
      "sourceKind": "checklists",
      "checklist": "Azure DevOps",
      "category": "DevOps Practice",
      "subcategory": "Practice",
      "id": "E01.06",
      "text": "Secure DevOps Governance",
      "description": "Mirror RBAC in DevOps",
      "severity": "Low",
      "waf": "Security",
      "link": "https://learn.microsoft.com/azure/cloud-adoption-framework/secure/best-practices/end-to-end-governance",
      "training": "https://learn.microsoft.com/learn/paths/architect-infrastructure-operations/",
      "sourcePath": "checklists/ado_checklist.en.json",
      "sourceUrl": "https://github.com/Azure/review-checklists/blob/main/checklists/ado_checklist.en.json",
      "normalizedAt": "2026-05-08T18:00:27.107Z",
      "provenance": {
        "technology": "normalized",
        "technologyStatus": "normalized",
        "category": "source",
        "subcategory": "source",
        "severity": "normalized",
        "waf": "normalized",
        "service": "unavailable",
        "description": "source"
      }
    },
    {
      "guid": "7633bd2a-1a27-4a76-9a90-be0e378ee293",
      "technology": "Azure DevOps",
      "technologySlug": "azure-devops-ado-checklist",
      "technologyStatus": "Preview",
      "technologyMaturityBucket": "Preview",
      "usageConfidence": "Medium",
      "technologyQualityScore": 89,
      "family": "Azure DevOps",
      "sourceKind": "checklists",
      "checklist": "Azure DevOps",
      "category": "DevOps Practice",
      "subcategory": "Practice",
      "id": "E01.07",
      "text": "Azure DevOps Governance",
      "description": "Governance when using CI/CD",
      "severity": "Medium",
      "waf": "Security",
      "link": "https://learn.microsoft.com/azure/architecture/example-scenario/governance/end-to-end-governance-in-azure",
      "training": "https://learn.microsoft.com/learn/paths/implement-resource-mgmt-security/",
      "sourcePath": "checklists/ado_checklist.en.json",
      "sourceUrl": "https://github.com/Azure/review-checklists/blob/main/checklists/ado_checklist.en.json",
      "normalizedAt": "2026-05-08T18:00:27.107Z",
      "provenance": {
        "technology": "normalized",
        "technologyStatus": "normalized",
        "category": "source",
        "subcategory": "source",
        "severity": "normalized",
        "waf": "normalized",
        "service": "unavailable",
        "description": "source"
      }
    }
  ]
}